Metadata-Version: 2.4
Name: filelock-lts-py314
Version: 2025.68146.1
Summary: filelock LTS tracker for Python 3.14 (redirects to official filelock >= 3.20.1)
License-Expression: Unlicense
Project-URL: Homepage, https://github.com/1minds3t/filelock-lts
Requires-Python: <3.15,>=3.14
License-File: LICENSE
Requires-Dist: filelock>=3.20.1
Dynamic: license-file
